mrsqm/mrsqm_wrapper.cpython-38-i386-linux-gnu.so
mrsqm/__init__.py
mrsqm-0.0.7.dist-info/METADATA
mrsqm-0.0.7.dist-info/top_level.txt
mrsqm-0.0.7.dist-info/WHEEL
mrsqm-0.0.7.dist-info/RECORD
mrsqm-0.0.7.dist-info/LICENSE
mrsqm.libs/libfftw3-3deb7d87.so.3.2.3
