Metadata-Version: 2.1
Name: mrsqm
Version: 0.0.7
Summary: MrSQM: Fast Time Series Classification with Symbolic Representations
Author: Thach Le Nguyen
Author-email: thalng@protonmail.com
Requires-Python: >=3.7
License-File: LICENSE
Requires-Dist: numpy >=1.18
Requires-Dist: pandas >=1.0.3
Requires-Dist: scikit-learn >=0.22
